CHANGES.txt
LICENSE.txt
MANIFEST.in
README.rst
setup.cfg
setup.py
projectkey/__init__.py
projectkey/command_class.py
projectkey/decorators.py
projectkey/interpreter.py
projectkey/k_runner.py
projectkey/run_commands.py
projectkey.egg-info/PKG-INFO
projectkey.egg-info/SOURCES.txt
projectkey.egg-info/dependency_links.txt
projectkey.egg-info/entry_points.txt
projectkey.egg-info/not-zip-safe
projectkey.egg-info/requires.txt
projectkey.egg-info/top_level.txt