Metadata-Version: 1.1
Name: projectkey
Version: 0.7
Summary: A tool for running a suite of custom project commands invoked via one key.
Home-page: https://github.com/crdoconnor/projectkey
Author: Colm O'Connor
Author-email: colm.oconnor.github@gmail.com
License: MIT
Keywords: development environment tool automation project
Platform: UNKNOWN
Classifier: Development Status :: 3 - Alpha
Classifier: Intended Audience :: Developers
Classifier: License :: OSI Approved :: MIT License
Classifier: Topic :: Software Development :: Build Tools
Classifier: Programming Language :: Python :: 2
Classifier: Programming Language :: Python :: 2.6
Classifier: Programming Language :: Python :: 2.7
